LICENSE
salesman_paypal/__init__.py
salesman_paypal/conf.py
salesman_paypal/payment.py
salesman_paypal/templates/salesman_paypal/cancel.html
salesman_paypal/templates/salesman_paypal/return.html
django_salesman_paypal-0.1.6.dist-info/LICENSE
django_salesman_paypal-0.1.6.dist-info/WHEEL
django_salesman_paypal-0.1.6.dist-info/METADATA
django_salesman_paypal-0.1.6.dist-info/RECORD
