Metadata-Version: 2.1
Name: django-salesman-paypal
Version: 0.1.6
Summary: PayPal payment integration for Salesman.
Home-page: https://pypi.org/project/django-salesman-paypal/
License: BSD-3-Clause
Keywords: PayPal,Salesman,e-commerce
Author: Dino Perovic
Author-email: dino.perovic@gmail.com
Requires-Python: >=3.8.1,<4.0
Classifier: Development Status :: 4 - Beta
Classifier: Framework :: Django
Classifier: Framework :: Django :: 3.1
Classifier: Framework :: Django :: 3.2
Classifier: Framework :: Django :: 4.0
Classifier: Framework :: Django :: 4.1
Classifier: Framework :: Wagtail
Classifier: Framework :: Wagtail :: 2
Classifier: Intended Audience :: Developers
Classifier: License :: OSI Approved :: BSD License
Classifier: Operating System :: OS Independent
Classifier: Programming Language :: Python :: 3
Classifier: Programming Language :: Python :: 3.10
Classifier: Programming Language :: Python :: 3.9
Classifier: Topic :: Internet
Requires-Dist: django-salesman (>=1.1.3)
Requires-Dist: paypal-checkout-serversdk (>=1.0.1,<1.1.0)
Project-URL: Repository, https://github.com/dinoperovic/django-salesman-paypal
